<?xml version="1.0" encoding="UTF-8"?>
<objects serializationModel="Studio.02.02.00">
	<object class="AudioFile" id="{0cff6a06-a3dc-4ae7-86c4-ff012faf8a9b}">
		<property name="assetPath">
			<value>music/Pizza_Tower_OST_-_Receiding_Hairline_Celebration_Party.wav</value>
		</property>
		<property name="isStreaming">
			<value>true</value>
		</property>
		<property name="frequencyInKHz">
			<value>48</value>
		</property>
		<property name="channelCount">
			<value>2</value>
		</property>
		<property name="length">
			<value>179.01712499999999</value>
		</property>
		<relationship name="masterAssetFolder">
			<destination>{a84aba2b-0040-4799-9e51-d1e20c3d1cf5}</destination>
		</relationship>
	</object>
</objects>
