<?xml version="1.0" encoding="UTF-8"?>
<objects serializationModel="Studio.02.02.00">
	<object class="AudioFile" id="{23c03d07-cb8a-4300-ab18-df4ce3abd37e}">
		<property name="assetPath">
			<value>music/Mr. Sauceman, ClascyJitto &amp; Post Elvis - Pizza Tower (Original Game Soundtrack - Bonus Tracks) - 01 The Oise has Arrived.wav</value>
		</property>
		<property name="isStreaming">
			<value>true</value>
		</property>
		<property name="frequencyInKHz">
			<value>48</value>
		</property>
		<property name="channelCount">
			<value>2</value>
		</property>
		<property name="length">
			<value>27.428562500000002</value>
		</property>
		<relationship name="masterAssetFolder">
			<destination>{a84aba2b-0040-4799-9e51-d1e20c3d1cf5}</destination>
		</relationship>
	</object>
</objects>
