<?xml version="1.0" encoding="UTF-8"?>
<objects serializationModel="Studio.02.02.00">
	<object class="AudioFile" id="{eee28dcf-6517-474d-a52c-6b4a80ba2873}">
		<property name="assetPath">
			<value>sfx/uppercut.wav</value>
		</property>
		<property name="frequencyInKHz">
			<value>48</value>
		</property>
		<property name="channelCount">
			<value>1</value>
		</property>
		<property name="length">
			<value>1.5945833333333332</value>
		</property>
		<relationship name="masterAssetFolder">
			<destination>{bf575252-09c1-4fff-a9f7-5be08d17b6ed}</destination>
		</relationship>
	</object>
</objects>
